<?xml version='1.0' ?> 
<strings>
	<string id='ABC1'>A</string>
	<string id='ABC2'>B</string>
	<string id='ABC3'>C</string>
	<string id='ABC4'>D</string>
	<string id='ABC5'>E</string>
	<string id='ABC6'>F</string>
	<string id='ABC7'>G</string>
	<string id='ABC8'>H</string>
	<string id='ABC9'>I</string>
	<string id='ABC10'>J</string>
	<string id='ABC11'>K</string>
	<string id='ABC12'>L</string>
	<string id='ABC13'>M</string>
	<string id='ABC14'>N</string>
	<string id='ABC15'>O</string>
	<string id='ABC16'>P</string>
	<string id='ABC17'>Q</string>
	<string id='ABC18'>R</string>
	<string id='ABC19'>S</string>
	<string id='ABC20'>T</string>
	<string id='ABC21'>U</string>
	<string id='ABC22'>V</string>
	<string id='ABC23'>W</string>
	<string id='ABC24'>X</string>
	<string id='ABC25'>Y</string>
	<string id='ABC26'>Z</string>
</strings>